README.md
setup.py
n2yo/__init__.py
n2yo/n2yo.py
n2yo/satellite_categories.py
n2yo_aio.egg-info/PKG-INFO
n2yo_aio.egg-info/SOURCES.txt
n2yo_aio.egg-info/dependency_links.txt
n2yo_aio.egg-info/top_level.txt
tests/__init__.py
tests/test_get_above.py
tests/test_get_radio_passes.py
tests/test_get_satellite_positions.py
tests/test_get_tle.py
tests/test_get_visual_passes.py