Metadata-Version: 2.1
Name: n2yo-aio
Version: 1.0.0
Summary: Asynchronous Python wrapper for the N2YO API.
Home-page: https://git.facorazza.com/facorazza/n2yo-aio
Author: Federico A. Corazza
Author-email: federico.corazza@live.it
License: UNKNOWN
Platform: UNKNOWN
Classifier: Programming Language :: Python :: 3
Classifier: License :: OSI Approved :: MIT License
Classifier: Operating System :: OS Independent
